<?xml version="1.0" encoding="utf-8"?>
<manifest xmlns="http://tizen.org/ns/packages" package="ug-bluetooth-efl" version="2.0.25" install-location="internal-only">
	<label>Bluetooth</label>
	<author email="dh79.pyun@samsung.com" href="www.samsung.com">DoHyun Pyun</author>
	<description>Bluetooth AppControl</description>
	<ui-application appid="ug-bluetooth-efl" exec="/usr/ug/bin/setting-bluetooth-efl" nodisplay="true" multiple="true" type="capp" taskmanage="false">
		<label>Bluetooth</label>
		<icon>org.tizen.bt-syspopup.png</icon>
		<application-service>
			<operation name="http://tizen.org/appcontrol/operation/send"/>
			<mime name="*/*"/>
		</application-service>
		<application-service>
			<operation name="http://tizen.org/appcontrol/operation/pick"/>
		</application-service>
	</ui-application>
</manifest>
